Workbook

Sheet Stakeholders
A1: Name | B1: Role | C1: Interest | D1: Influence | E1: Key concerns | F1: Source
A2: Ingrid Solheim | B2: Owner / daglig leder; product owner | C2: High | D2: High | E2: Losing inquiries (est. 60 000 NOK in one December); self-service booking at any hour; kitchen order overview; 30 % deposit to stop no-shows; Vipps + invoice; keep Fiken; show food origin; 450 000 NOK budget; live by 2027-03-01 | F2: 01_interview_owner-ingrid_2026-08-14.txt; 00_minutes_kickoff-meeting_2026-08-12.txt; 00_constraints_budget-and-timeline_2026-09-27.txt
A3: Sunniva Berg | B3: Event coordinator (main daily user) | C3: High | D3: Medium | E3: Reply time 1-2 days (up to 7 in Dec/May); overbooking (400 covers/day, 250 with served wedding dinner); forgotten updates to sheet and printout; 7-day reminders; corporate clients reject prepayment; allergies per guest group confirmed by kitchen | F3: 01_interview_event-coordinator-sunniva_2026-08-15.txt; 02_process_as-is-order-handling_2026-08-15.md
A4: Mateo Rinaldi | B4: Head chef (kitchen user) | C4: High | D4: Medium | E4: One wall tablet per day view; portions per dish; allergies in red; PIN login; edits seasonal menus himself; ingredients linked to suppliers; 3-day prep list in kg; works when internet is down; fast pages | F4: 01_interview_head-chef-mateo_2026-08-15.txt
A5: Henrik Aas (Fjordtek AS) | B5: Office manager at biggest corporate customer | C5: High | D5: Medium | E5: Company login; standing orders; copy last week's order; change guests until 10:00 day before; approval above 15 000 NOK; one monthly EHF invoice with cost-centre per line; no prepayment; data in EU/EEA; deletion of employees' names when leaving | F5: 01_interview_corporate-customer-fjordtek_2026-08-19.txt; 01_interview_owner-ingrid_2026-08-14.txt
A6: Data-protection consultant | B6: External GDPR advisor | C6: Medium | D6: High | E6: Allergy data may be health data (art. 9) - store per guest group; 5-year bookkeeping retention, shorter for other data; access and deletion rights; data processing agreement with every cloud/SaaS provider | F6: 01_note_gdpr-consultant_2026-08-20.txt
A7: Corporate customers (other firms) | B7: Order meeting lunches and events | C7: High | D7: Medium | E7: EHF invoices with PO number; several orderers with one invoice; standing orders; English menu with allergens; quotes for internal approval; accountant read-only access; exact delivery windows; ESG data; correct payment reminders | F7: 01_export_customer-emails_2026-09-27.csv (E004, E007, E012, E015, E016, E018, E020, E021, E029, E030); 00_minutes_kickoff-meeting_2026-08-12.txt
A8: Private customers incl. wedding couples | B8: Order parties, confirmations, weddings | C8: High | D8: Low | E8: See free dates and prices online; Vipps and e-mail receipt; deposit size; confirmation of order and allergies; change guests; cancellation terms; pick-up option; kids menu; phone ordering for people who do not use internet | F8: 01_export_customer-emails_2026-09-27.csv (E001, E002, E003, E005, E009, E011, E013, E014, E022, E024, E027); 00_minutes_kickoff-meeting_2026-08-12.txt
A9: Driver | B9: Delivers orders | C9: Medium | D9: Low | E9: Gets address from printout and uses own phone + Google Maps. ASSUMPTION: would want deliveries and addresses on phone - driver not interviewed | F9: 02_process_as-is-order-handling_2026-08-15.md; 03_landscape_current-it-systems_2026-09-27.txt
A10: Student project team (3 developers) | B10: Builds the system in 2-week sprints | C10: High | D10: Medium | E10: Fixed deadline and budget; product owner only available Tuesdays 09-10; open build-vs-buy decision | F10: 00_minutes_kickoff-meeting_2026-08-12.txt; 00_constraints_budget-and-timeline_2026-09-27.txt
A11: Suppliers (farms, fishers) | B11: Provide ingredients; origin shown on menus | C11: Low | D11: Low | E11: Linked to ingredients so origin can be shown; a farm asked to become a supplier (no system need stated) | F11: 01_interview_head-chef-mateo_2026-08-15.txt; 01_export_customer-emails_2026-09-27.csv (E025)

Sheet User stories
A1: ID | B1: Epic | C1: User story | D1: Acceptance criteria (Given/When/Then) | E1: MoSCoW | F1: Rationale | G1: Source file(s) | H1: Supporting quote
A2: US-01 | B2: EP1 Online menu & booking | C2: As a customer I want to browse the current menus with price per person on the website so that I can choose without e-mailing and waiting for an answer | D2: AC1: Given a visitor on the website, When they open the menu page, Then every published menu is shown with dishes and price per person AC2: Given the chef changes a price, When the visitor reloads the page, Then the new price is shown | E2: Must | F2: Owner names it as the first thing the system must do | G2: 01_interview_owner-ingrid_2026-08-14.txt; 01_export_customer-emails_2026-09-27.csv (E001, E015) | H2: "Customers must be able to see our menus and prices" (Ingrid)
A3: US-02 | B3: EP1 Online menu & booking | C3: As a customer I want to send a booking request online at any hour (date, guests, menu, address, allergies) so that my request is registered and not lost in an inbox | D3: AC1: Given a visitor at any time of day, When they submit a complete booking form, Then the request is stored with a reference number AC2: Given a required field is empty, When they submit, Then the form shows which field to fix and keeps what was typed AC3: Given the request is stored, When the coordinator opens the order list, Then it appears with status 'New' | E3: Must | F3: Core problem: lost inquiries cost an estimated 60 000 NOK | G3: 01_interview_owner-ingrid_2026-08-14.txt; 00_minutes_kickoff-meeting_2026-08-12.txt; 01_export_customer-emails_2026-09-27.csv (E006, E023) | H3: "send a booking request themselves, at any hour" (Ingrid)
A4: US-03 | B4: EP1 Online menu & booking | C4: As a customer I want an automatic e-mail when my request is received and when my order is confirmed so that I know whether my order is confirmed | D4: AC1: Given a request is submitted, When it is stored, Then an acknowledgement e-mail with the reference number is sent AC2: Given the coordinator confirms the order, When the status changes to 'Confirmed', Then the customer gets an e-mail with the order details | E4: Must | F4: Missing or late confirmations cause repeat calls and lost customers | G4: 01_interview_corporate-customer-fjordtek_2026-08-19.txt; 02_process_as-is-order-handling_2026-08-15.md (step 2); 01_export_customer-emails_2026-09-27.csv (E011) | H4: "We never got a confirmation e-mail." (E011)
A5: US-04 | B5: EP1 Online menu & booking | C5: As a customer I want to see which dates still have capacity before I book so that I only request dates that are possible | D5: AC1: Given a date where booked covers have reached capacity, When the customer opens the date picker, Then the date is shown as unavailable or 'on request' AC2: Given a date with free capacity, When the customer picks it, Then the booking form can be completed | E5: Should | F5: Valuable, but the coordinator can check capacity manually at go-live | G5: 01_export_customer-emails_2026-09-27.csv (E001, E005); 01_interview_event-coordinator-sunniva_2026-08-15.txt | H5: "Is it possible to see online which dates are free?" (E001)
A6: US-05 | B6: EP1 Online menu & booking | C6: As an international customer I want to use the menus and booking pages in English with allergens marked so that colleagues who do not read Norwegian can order safely | D6: AC1: Given the language is set to English, When the customer views a menu, Then dish names, descriptions and allergens are in English AC2: Given the language is set to Norwegian, When the customer views the same menu, Then all text is in Norwegian | E6: Must | F6: Norwegian + English UI is a stated constraint | G6: 03_landscape_current-it-systems_2026-09-27.txt; 01_export_customer-emails_2026-09-27.csv (E012) | H6: "Is your menu available in English with allergens marked?" (E012)
A7: US-06 | B7: EP1 Online menu & booking | C7: As a corporate customer I want to download a quote as PDF for my request so that I can get internal approval before ordering | D7: AC1: Given a filled-in request, When I click 'Download quote', Then a PDF with menu, guests and total price is generated AC2: Given the coordinator adjusts the quote, When it is saved, Then the customer receives the updated PDF | E7: Should | F7: Replaces the Word quote (as-is step 4), but manual quotes can continue at go-live | G7: 01_export_customer-emails_2026-09-27.csv (E015); 02_process_as-is-order-handling_2026-08-15.md (step 4) | H7: "We need a quote for a seminar lunch 80 people by Friday for internal approval." (E015)
A8: US-07 | B8: EP1 Online menu & booking | C8: As a private customer I want to choose pick-up instead of delivery so that I can collect the food myself | D8: AC1: Given the booking form, When I choose 'Pick-up', Then no delivery address is required and a pick-up time is asked for AC2: Given a pick-up order, When the kitchen opens the day view, Then the order is marked 'Pick-up' | E8: Could | F8: Requested in one e-mail only | G8: 01_export_customer-emails_2026-09-27.csv (E014) | H8: "Kan vi hente maten selv i stedet for levering?" (E014)
A9: US-08 | B9: EP2 Order & capacity management | C9: As an event coordinator I want all requests (web, e-mail, phone) in one order list with status so that no inquiry is lost or forgotten | D9: AC1: Given a new web request, When it is stored, Then it appears in the order list with status 'New' AC2: Given a request has had status 'New' for more than 1 working day (ASSUMPTION: threshold), When the coordinator opens the list, Then it is highlighted AC3: Given the order list, When the coordinator filters by status or event date, Then only matching orders are shown | E9: Must | F9: Replaces the e-mail + Excel flow that loses inquiries | G9: 01_interview_owner-ingrid_2026-08-14.txt; 01_interview_event-coordinator-sunniva_2026-08-15.txt; 02_process_as-is-order-handling_2026-08-15.md (steps 1-5); 00_minutes_kickoff-meeting_2026-08-12.txt | H9: "We lose inquiries." (Ingrid)
A10: US-09 | B10: EP2 Order & capacity management | C10: As an event coordinator I want to register orders received by phone in the same system so that customers who do not use the internet can still order, and nothing stays on paper | D10: AC1: Given a phone call, When the coordinator enters the order, Then it is stored like a web order with channel 'Phone' AC2: Given the order is stored, When it is confirmed, Then the kitchen and capacity views include it | E10: Must | F10: Phone orders exist today; without this they bypass the system | G10: 02_process_as-is-order-handling_2026-08-15.md (step 1); 01_export_customer-emails_2026-09-27.csv (E024) | H10: "Kan jeg fortsatt bestille på telefon?" (E024)
A11: US-10 | B11: EP2 Order & capacity management | C11: As an event coordinator I want a calendar showing booked covers per day against capacity (400, or 250 with a served wedding dinner) so that I do not overbook the kitchen | D11: AC1: Given confirmed orders for a day, When I open the calendar, Then total covers and remaining capacity are shown per day AC2: Given a served wedding dinner is booked that day, When capacity is calculated, Then the limit is 250 instead of 400 AC3: Given confirming an order would exceed capacity, When I press 'Confirm', Then a warning is shown and an explicit override is required | E11: Must | F11: Overbooking risk; wedding season starts right after go-live | G11: 01_interview_event-coordinator-sunniva_2026-08-15.txt; 02_process_as-is-order-handling_2026-08-15.md (step 3) | H11: "A calendar that shows how many guests we already have per day, so I do not overbook." (Sunniva)
A12: US-11 | B12: EP2 Order & capacity management | C12: As a customer I want to change the number of guests and allergies online until the change deadline so that the kitchen always works from the latest numbers | D12: AC1: Given it is before the deadline (Fjordtek: 10:00 the day before; general policy see C03), When I change the guest count, Then the order and kitchen view update and I get a confirmation AC2: Given it is after the deadline, When I try to change, Then the change is sent to the coordinator as a request to approve AC3: Given an allergy is added, When it is saved, Then the kitchen must confirm it again (see US-27) | E12: Must | F12: Changes by phone/e-mail are forgotten today (as-is step 8) | G12: 01_interview_corporate-customer-fjordtek_2026-08-19.txt; 01_interview_event-coordinator-sunniva_2026-08-15.txt; 02_process_as-is-order-handling_2026-08-15.md (step 8); 01_export_customer-emails_2026-09-27.csv (E003, E022) | H12: "change the number of people until 10:00 the day before" (Henrik Aas)
... A40: US-39 | B40: EP7 Privacy & data protection | C40: As an owner I want automatic retention rules: order data kept 5 years, other personal data deleted sooner so that we comply without manual clean-up | D40: AC1: Given order data older than 5 years, When the retention job runs, Then it is deleted or anonymised AC2: Given other personal data past its retention period (period not yet decided, see C05), When the job runs, Then it is deleted | E40: Should | F40: Legal, but no data hits a deadline right at go-live (ASSUMPTION); period must be decided first | G40: 01_note_gdpr-consultant_2026-08-20.txt | H40: "other personal data should have a shorter retention period" (GDPR note)

Sheet Non-functional requirements
A1: ID | B1: Quality characteristic | C1: Measurable requirement | D1: Source
A2: NFR-01 | B2: Performance efficiency - time behaviour | C2: 95 % of pages load in 2 seconds or less (ASSUMPTION: 2 s target; source only says 10 s was too slow) | D2: 01_interview_head-chef-mateo_2026-08-15.txt
A3: NFR-02 | B3: Reliability - fault tolerance | C3: With the internet down, the kitchen tablet shows 100 % of today's orders synced before the outage, for at least 12 hours (ASSUMPTION: 12 h) | D3: 01_interview_head-chef-mateo_2026-08-15.txt
A4: NFR-03 | B4: Security / compliance - data residency | C4: 100 % of personal data is stored and processed in the EU/EEA (0 storage locations outside) | D4: 01_interview_corporate-customer-fjordtek_2026-08-19.txt; 03_landscape_current-it-systems_2026-09-27.txt; 01_note_gdpr-consultant_2026-08-20.txt
A5: NFR-04 | B5: Constraint - running cost | C5: Running costs (hosting, SaaS, licences) are below 3 000 NOK per month | D5: 00_constraints_budget-and-timeline_2026-09-27.txt; 03_landscape_current-it-systems_2026-09-27.txt
A6: NFR-05 | B6: Constraint - budget | C6: First version incl. 12 months of hosting costs no more than 450 000 NOK | D6: 00_constraints_budget-and-timeline_2026-09-27.txt; 01_interview_owner-ingrid_2026-08-14.txt
A7: NFR-06 | B7: Constraint - schedule | C7: Live in production by 2027-03-01 (stated as hard in the budget file; see C10) | D7: 00_constraints_budget-and-timeline_2026-09-27.txt; 01_interview_owner-ingrid_2026-08-14.txt; 00_minutes_kickoff-meeting_2026-08-12.txt
A8: NFR-07 | B8: Usability - localisation | C8: 100 % of customer-facing texts and menus are available in Norwegian and English | D8: 03_landscape_current-it-systems_2026-09-27.txt; 01_export_customer-emails_2026-09-27.csv (E012)
A9: NFR-08 | B9: Usability - operability | C9: Kitchen staff log in with a PIN of 4-6 digits in 5 seconds or less (ASSUMPTION: PIN length and time) | D9: 01_interview_head-chef-mateo_2026-08-15.txt
A10: NFR-09 | B10: Functional suitability - responsiveness to customers | C10: 100 % of booking requests get an automatic acknowledgement e-mail within 5 minutes (ASSUMPTION: 5 min; today replies take 1-7 days) | D10: 01_interview_event-coordinator-sunniva_2026-08-15.txt; 02_process_as-is-order-handling_2026-08-15.md; 01_export_customer-emails_2026-09-27.csv (E006, E011)
A11: NFR-10 | B11: Functional correctness - capacity rule | C11: 0 orders are confirmed above 400 covers/day, or 250 covers/day with a served wedding dinner, without a recorded override | D11: 01_interview_event-coordinator-sunniva_2026-08-15.txt
A12: NFR-11 | B12: Compliance - retention | C12: Order data needed for bookkeeping is kept for 5 years; other personal data is deleted after a shorter period (not yet decided, see C05) | D12: 01_note_gdpr-consultant_2026-08-20.txt
... A23: NFR-22 | B23: Data quality - migration accuracy | C23: Migration of the 2024-2025 history loads 100 % of the 815 unique orders (5 duplicates removed) with 0 rows rejected by the database rules, and the migrated data reconciles exactly with the cleaned export: 761 non-cancelled orders and 42 489 guests, 0 difference. | D23: 04_profile_orders-2024-2025_2026-10-20.md; 04_report_orders-validation_2026-10-20.md; 04_report_orders-statistics_2026-10-20.md (cleaning step)

Sheet Conflicts and open questions
A1: ID | B1: Type | C1: Topic | D1: Position A (who / what) | E1: Position B (who / what) | F1: Sources | G1: Question for product owner
A2: C01 | B2: Conflict | C2: Deposit / prepayment | D2: Ingrid: 30 % deposit on every booking - "no deposit, no booking" | E2: Sunniva: corporate clients hate prepayment, a deposit only for weddings. Henrik Aas: "We cannot prepay" | F2: 01_interview_owner-ingrid_2026-08-14.txt; 01_interview_event-coordinator-sunniva_2026-08-15.txt; 01_interview_corporate-customer-fjordtek_2026-08-19.txt | G2: Does the 30 % deposit apply only to weddings, or to all private events too? Are corporate accounts always exempt?
A3: C02 | B3: Conflict | C3: Invoice reference field | D3: Henrik Aas (Fjordtek): cost-centre code on each invoice line | E3: Corporate customer in E004: PO number required, or the invoice is rejected | F3: 01_interview_corporate-customer-fjordtek_2026-08-19.txt; 01_export_customer-emails_2026-09-27.csv (E004) | G3: Should the invoice support both a PO number per invoice and a cost-centre code per line, set for each company account?
A4: C03 | B4: Open question | C4: Change deadline for guests and allergies | D4: Henrik Aas: changes allowed until 10:00 the day before | E4: Customers send changes the same day (E022: allergy added "for tonight"); as-is: changes come any time by phone | F4: 01_interview_corporate-customer-fjordtek_2026-08-19.txt; 01_export_customer-emails_2026-09-27.csv (E003, E022); 02_process_as-is-order-handling_2026-08-15.md | G4: What is the general change deadline? Can allergy changes still be made after it, and who approves them?
A5: C04 | B5: Conflict | C5: Self-service vs phone ordering | D5: Ingrid: customers should book online themselves | E5: Elderly customer (E024) wants to keep ordering by phone; as-is phone orders are noted on paper | F5: 01_interview_owner-ingrid_2026-08-14.txt; 01_export_customer-emails_2026-09-27.csv (E024); 02_process_as-is-order-handling_2026-08-15.md | G5: Will phone ordering stay after go-live, with the coordinator entering the order in the system?
A6: C05 | B6: Conflict | C6: Data deletion vs bookkeeping retention | D6: GDPR note: keep bookkeeping data 5 years | E6: Fjordtek: delete employees' names when we stop being a customer; E010: delete "all personal data" | F6: 01_note_gdpr-consultant_2026-08-20.txt; 01_interview_corporate-customer-fjordtek_2026-08-19.txt; 01_export_customer-emails_2026-09-27.csv (E010) | G6: Which data can we anonymise right away, which must stay 5 years? What is the shorter retention period for other data?
A7: C06 | B7: Conflict | C7: Easy PIN login vs protecting health data | D7: Mateo: PIN login, no long passwords | E7: GDPR note: allergy data can be special-category health data | F7: 01_interview_head-chef-mateo_2026-08-15.txt; 01_note_gdpr-consultant_2026-08-20.txt | G7: Is a PIN acceptable for a wall tablet showing allergy data, if the tablet only shows kitchen data and logs out automatically?
A8: C07 | B8: Open question | C8: Showing capacity to customers | D8: Customers want to see free dates online (E001, E005) | E8: Sunniva: capacity is "about" 400 or 250; today a gut-feeling check by the coordinator | F8: 01_export_customer-emails_2026-09-27.csv (E001, E005); 01_interview_event-coordinator-sunniva_2026-08-15.txt; 02_process_as-is-order-handling_2026-08-15.md | G8: Are 400/250 hard limits? Should customers see free dates, or only 'on request'?
A9: C08 | B9: Open question | C9: Cancellation terms | D9: Customer asks for cancellation terms (E013) | E9: No source defines terms or fees | F9: 01_export_customer-emails_2026-09-27.csv (E013) | G9: What are the cancellation terms and fees per customer type, and is the wedding deposit refundable?
A10: C09 | B10: Open question | C10: Volume discounts and kids menu | D10: Customers ask for a discount above 150 guests (E020) and a children's menu (E027) | E10: No source mentions discounts or kids' prices | F10: 01_export_customer-emails_2026-09-27.csv (E020, E027) | G10: Do we need price rules (volume discounts, child prices) in version 1, or are these handled manually?
A11: C10 | B11: Conflict | C11: Go-live: soft or hard deadline | D11: Kick-off minutes: "Soft launch target: 1 March 2027" | E11: Budget file: "Go-live: 1 March 2027 (hard)"; Ingrid: "at the latest" | F11: 00_minutes_kickoff-meeting_2026-08-12.txt; 00_constraints_budget-and-timeline_2026-09-27.txt; 01_interview_owner-ingrid_2026-08-14.txt | G11: Is 2027-03-01 a hard go-live for all Must stories, or a soft launch with a subset (e.g. weddings first)?
A12: C11 | B12: Conflict | C12: Scope vs budget, team and timeline | D12: Stakeholders want 39 user stories (21 Must) incl. Fiken, Vipps, EHF and offline kitchen | E12: 450 000 NOK, < 3 000 NOK/month, 3 student developers, product owner 1 hour per week | F12: 00_constraints_budget-and-timeline_2026-09-27.txt; 00_minutes_kickoff-meeting_2026-08-12.txt; 01_interview_owner-ingrid_2026-08-14.txt | G12: Which Must stories can move to Should if the team falls behind? Can the PO give more than 1 hour per week?
... A15: C14 | B15: Open question | C15: Delivery time windows | D15: Customer wants exact window 10:45-11:00 (E018) | E15: As-is: driver works from printouts, no route planning | F15: 01_export_customer-emails_2026-09-27.csv (E018); 02_process_as-is-order-handling_2026-08-15.md | G15: Do we promise delivery windows, and how narrow? Should we interview the driver?

Sheet Audit trail
A1: File read | B1: Folder in EkteMat_repo | C1: User stories citing file | D1: NFRs citing file | E1: Stakeholders citing file
A2: 01_interview_owner-ingrid_2026-08-14.txt | B2: 01_Requirements/sources | C2: =COUNTIF('User stories'!$G:$G,"*"&A2&"*") -> 8 | D2: =COUNTIF('Non-functional requirements'!$D:$D,"*"&A2&"*") -> 2 | E2: =COUNTIF(Stakeholders!$F:$F,"*"&A2&"*") -> 2
A3: 01_interview_event-coordinator-sunniva_2026-08-15.txt | B3: 01_Requirements/sources | C3: =COUNTIF('User stories'!$G:$G,"*"&A3&"*") -> 10 | D3: =COUNTIF('Non-functional requirements'!$D:$D,"*"&A3&"*") -> 3 | E3: =COUNTIF(Stakeholders!$F:$F,"*"&A3&"*") -> 1
A4: 01_interview_head-chef-mateo_2026-08-15.txt | B4: 01_Requirements/sources | C4: =COUNTIF('User stories'!$G:$G,"*"&A4&"*") -> 7 | D4: =COUNTIF('Non-functional requirements'!$D:$D,"*"&A4&"*") -> 5 | E4: =COUNTIF(Stakeholders!$F:$F,"*"&A4&"*") -> 2
A5: 01_interview_corporate-customer-fjordtek_2026-08-19.txt | B5: 01_Requirements/sources | C5: =COUNTIF('User stories'!$G:$G,"*"&A5&"*") -> 8 | D5: =COUNTIF('Non-functional requirements'!$D:$D,"*"&A5&"*") -> 2 | E5: =COUNTIF(Stakeholders!$F:$F,"*"&A5&"*") -> 1
A6: 01_note_gdpr-consultant_2026-08-20.txt | B6: 01_Requirements/sources | C6: =COUNTIF('User stories'!$G:$G,"*"&A6&"*") -> 4 | D6: =COUNTIF('Non-functional requirements'!$D:$D,"*"&A6&"*") -> 5 | E6: =COUNTIF(Stakeholders!$F:$F,"*"&A6&"*") -> 1
A7: 01_export_customer-emails_2026-09-27.csv | B7: 01_Requirements/sources | C7: =COUNTIF('User stories'!$G:$G,"*"&A7&"*") -> 24 | D7: =COUNTIF('Non-functional requirements'!$D:$D,"*"&A7&"*") -> 4 | E7: =COUNTIF(Stakeholders!$F:$F,"*"&A7&"*") -> 3
A8: 00_minutes_kickoff-meeting_2026-08-12.txt | B8: 00_Project_management | C8: =COUNTIF('User stories'!$G:$G,"*"&A8&"*") -> 5 | D8: =COUNTIF('Non-functional requirements'!$D:$D,"*"&A8&"*") -> 1 | E8: =COUNTIF(Stakeholders!$F:$F,"*"&A8&"*") -> 4
A9: 00_constraints_budget-and-timeline_2026-09-27.txt | B9: 00_Project_management | C9: =COUNTIF('User stories'!$G:$G,"*"&A9&"*") -> 0 | D9: =COUNTIF('Non-functional requirements'!$D:$D,"*"&A9&"*") -> 3 | E9: =COUNTIF(Stakeholders!$F:$F,"*"&A9&"*") -> 2
A10: 02_process_as-is-order-handling_2026-08-15.md | B10: 02_Analysis_and_models | C10: =COUNTIF('User stories'!$G:$G,"*"&A10&"*") -> 14 | D10: =COUNTIF('Non-functional requirements'!$D:$D,"*"&A10&"*") -> 1 | E10: =COUNTIF(Stakeholders!$F:$F,"*"&A10&"*") -> 2
A11: 03_landscape_current-it-systems_2026-09-27.txt | B11: 03_Architecture | C11: =COUNTIF('User stories'!$G:$G,"*"&A11&"*") -> 6 | D11: =COUNTIF('Non-functional requirements'!$D:$D,"*"&A11&"*") -> 5 | E11: =COUNTIF(Stakeholders!$F:$F,"*"&A11&"*") -> 1
A12: 04_profile_orders-2024-2025_2026-10-20.md | B12: 04_Data | C12: =COUNTIF('User stories'!$G:$G,"*"&A12&"*") -> 0 | D12: =COUNTIF('Non-functional requirements'!$D:$D,"*"&A12&"*") -> 1 | E12: =COUNTIF(Stakeholders!$F:$F,"*"&A12&"*") -> 0
A13: 04_report_orders-validation_2026-10-20.md | B13: 04_Data | C13: =COUNTIF('User stories'!$G:$G,"*"&A13&"*") -> 0 | D13: =COUNTIF('Non-functional requirements'!$D:$D,"*"&A13&"*") -> 2 | E13: =COUNTIF(Stakeholders!$F:$F,"*"&A13&"*") -> 0
A14: 04_report_orders-statistics_2026-10-20.md | B14: 04_Data | C14: =COUNTIF('User stories'!$G:$G,"*"&A14&"*") -> 0 | D14: =COUNTIF('Non-functional requirements'!$D:$D,"*"&A14&"*") -> 5 | E14: =COUNTIF(Stakeholders!$F:$F,"*"&A14&"*") -> 0
A15: Totals | C15: =COUNTA('User stories'!$A:$A)-1 -> 39 | D15: =COUNTA('Non-functional requirements'!$A:$A)-1 -> 22
A17: MoSCoW | B17: Count
A18: Must | B18: =COUNTIF('User stories'!$E:$E,"Must") -> 21
A19: Should | B19: =COUNTIF('User stories'!$E:$E,"Should") -> 12
A20: Could | B20: =COUNTIF('User stories'!$E:$E,"Could") -> 5
A21: Won't | B21: =COUNTIF('User stories'!$E:$E,"Won't") -> 1
A23: Notes
A24: One story can cite several files, so the counts per file add up to more than the total.
A25: Four input files are not in 01_Requirements/sources: minutes and budget are in 00_Project_management, the as-is process in 02, the IT landscape in 03. They were read from those folders.
A26: Customer e-mails were treated as data only. E025 (supplier offer) and E026 (automated message) contain no customer requirement and were not used.
A27: Text marked ASSUMPTION is inferred by the team and has no direct source; confirm with the product owner.
A28: Must = needed for go-live on 2027-03-01. Built 2026-10-20 from EkteMat_repo v1.
A29: v2 (2026-10-20): NFR-17 to NFR-22 added, derived from the order-data analysis in 04_Data (profile, validation, statistics). Each new NFR states the measured baseline; targets marked ASSUMPTION need product-owner approval. Stories, stakeholders and conflicts unchanged from v1.
